[{"idCapteur":2621,"numCapteur":0,"intCapteur":0,"idenCapteur":"CAPTEUR_0","etat":"ALLUME"},{"idCapteur":2622,"numCapteur":1,"intCapteur":0,"idenCapteur":"CAPTEUR_1","etat":"ALLUME"},{"idCapteur":2623,"numCapteur":2,"intCapteur":0,"idenCapteur":"CAPTEUR_2","etat":"ALLUME"},{"idCapteur":2624,"numCapteur":3,"intCapteur":0,"idenCapteur":"CAPTEUR_3","etat":"ALLUME"},{"idCapteur":2625,"numCapteur":4,"intCapteur":0,"idenCapteur":"CAPTEUR_4","etat":"ALLUME"},{"idCapteur":2626,"numCapteur":5,"intCapteur":0,"idenCapteur":"CAPTEUR_5","etat":"ALLUME"},{"idCapteur":2627,"numCapteur":6,"intCapteur":0,"idenCapteur":"CAPTEUR_6","etat":"ALLUME"},{"idCapteur":2628,"numCapteur":7,"intCapteur":0,"idenCapteur":"CAPTEUR_7","etat":"ALLUME"},{"idCapteur":2629,"numCapteur":8,"intCapteur":0,"idenCapteur":"CAPTEUR_8","etat":"ALLUME"},{"idCapteur":2630,"numCapteur":9,"intCapteur":0,"idenCapteur":"CAPTEUR_9","etat":"ALLUME"},{"idCapteur":2631,"numCapteur":10,"intCapteur":0,"idenCapteur":"CAPTEUR_10","etat":"ALLUME"},{"idCapteur":2632,"numCapteur":11,"intCapteur":0,"idenCapteur":"CAPTEUR_11","etat":"ALLUME"},{"idCapteur":2633,"numCapteur":12,"intCapteur":0,"idenCapteur":"CAPTEUR_12","etat":"ALLUME"},{"idCapteur":2634,"numCapteur":13,"intCapteur":0,"idenCapteur":"CAPTEUR_13","etat":"ALLUME"},{"idCapteur":2635,"numCapteur":14,"intCapteur":0,"idenCapteur":"CAPTEUR_14","etat":"ALLUME"},{"idCapteur":2636,"numCapteur":15,"intCapteur":0,"idenCapteur":"CAPTEUR_15","etat":"ALLUME"},{"idCapteur":2637,"numCapteur":16,"intCapteur":0,"idenCapteur":"CAPTEUR_16","etat":"ALLUME"},{"idCapteur":2638,"numCapteur":17,"intCapteur":0,"idenCapteur":"CAPTEUR_17","etat":"ALLUME"},{"idCapteur":2639,"numCapteur":18,"intCapteur":0,"idenCapteur":"CAPTEUR_18","etat":"ALLUME"},{"idCapteur":2640,"numCapteur":19,"intCapteur":0,"idenCapteur":"CAPTEUR_19","etat":"ALLUME"},{"idCapteur":2641,"numCapteur":20,"intCapteur":0,"idenCapteur":"CAPTEUR_20","etat":"ALLUME"},{"idCapteur":2642,"numCapteur":21,"intCapteur":0,"idenCapteur":"CAPTEUR_21","etat":"ALLUME"},{"idCapteur":2643,"numCapteur":22,"intCapteur":0,"idenCapteur":"CAPTEUR_22","etat":"ALLUME"},{"idCapteur":2644,"numCapteur":23,"intCapteur":0,"idenCapteur":"CAPTEUR_23","etat":"ALLUME"},{"idCapteur":2645,"numCapteur":24,"intCapteur":0,"idenCapteur":"CAPTEUR_24","etat":"ALLUME"},{"idCapteur":2646,"numCapteur":25,"intCapteur":0,"idenCapteur":"CAPTEUR_25","etat":"ALLUME"},{"idCapteur":2647,"numCapteur":26,"intCapteur":0,"idenCapteur":"CAPTEUR_26","etat":"ALLUME"},{"idCapteur":2648,"numCapteur":27,"intCapteur":0,"idenCapteur":"CAPTEUR_27","etat":"ALLUME"},{"idCapteur":2649,"numCapteur":28,"intCapteur":0,"idenCapteur":"CAPTEUR_28","etat":"ALLUME"},{"idCapteur":2650,"numCapteur":29,"intCapteur":0,"idenCapteur":"CAPTEUR_29","etat":"ALLUME"},{"idCapteur":2651,"numCapteur":30,"intCapteur":0,"idenCapteur":"CAPTEUR_30","etat":"ALLUME"},{"idCapteur":2652,"numCapteur":31,"intCapteur":0,"idenCapteur":"CAPTEUR_31","etat":"ALLUME"},{"idCapteur":2653,"numCapteur":32,"intCapteur":0,"idenCapteur":"CAPTEUR_32","etat":"ALLUME"},{"idCapteur":2654,"numCapteur":33,"intCapteur":0,"idenCapteur":"CAPTEUR_33","etat":"ALLUME"},{"idCapteur":2655,"numCapteur":34,"intCapteur":0,"idenCapteur":"CAPTEUR_34","etat":"ALLUME"},{"idCapteur":2656,"numCapteur":35,"intCapteur":0,"idenCapteur":"CAPTEUR_35","etat":"ALLUME"},{"idCapteur":2657,"numCapteur":36,"intCapteur":0,"idenCapteur":"CAPTEUR_36","etat":"ALLUME"},{"idCapteur":2658,"numCapteur":37,"intCapteur":0,"idenCapteur":"CAPTEUR_37","etat":"ALLUME"},{"idCapteur":2659,"numCapteur":38,"intCapteur":0,"idenCapteur":"CAPTEUR_38","etat":"ALLUME"},{"idCapteur":2660,"numCapteur":39,"intCapteur":0,"idenCapteur":"CAPTEUR_39","etat":"ALLUME"},{"idCapteur":2661,"numCapteur":40,"intCapteur":0,"idenCapteur":"CAPTEUR_40","etat":"ALLUME"},{"idCapteur":2662,"numCapteur":41,"intCapteur":0,"idenCapteur":"CAPTEUR_41","etat":"ALLUME"},{"idCapteur":2663,"numCapteur":42,"intCapteur":0,"idenCapteur":"CAPTEUR_42","etat":"ALLUME"},{"idCapteur":2664,"numCapteur":43,"intCapteur":0,"idenCapteur":"CAPTEUR_43","etat":"ALLUME"},{"idCapteur":2665,"numCapteur":44,"intCapteur":0,"idenCapteur":"CAPTEUR_44","etat":"ALLUME"},{"idCapteur":2666,"numCapteur":45,"intCapteur":0,"idenCapteur":"CAPTEUR_45","etat":"ALLUME"},{"idCapteur":2667,"numCapteur":46,"intCapteur":0,"idenCapteur":"CAPTEUR_46","etat":"ALLUME"},{"idCapteur":2668,"numCapteur":47,"intCapteur":0,"idenCapteur":"CAPTEUR_47","etat":"ALLUME"},{"idCapteur":2669,"numCapteur":48,"intCapteur":0,"idenCapteur":"CAPTEUR_48","etat":"ALLUME"},{"idCapteur":2670,"numCapteur":49,"intCapteur":0,"idenCapteur":"CAPTEUR_49","etat":"ALLUME"},{"idCapteur":2671,"numCapteur":50,"intCapteur":0,"idenCapteur":"CAPTEUR_50","etat":"ALLUME"},{"idCapteur":2672,"numCapteur":51,"intCapteur":0,"idenCapteur":"CAPTEUR_51","etat":"ALLUME"},{"idCapteur":2673,"numCapteur":52,"intCapteur":0,"idenCapteur":"CAPTEUR_52","etat":"ALLUME"},{"idCapteur":2674,"numCapteur":53,"intCapteur":0,"idenCapteur":"CAPTEUR_53","etat":"ALLUME"},{"idCapteur":2675,"numCapteur":54,"intCapteur":0,"idenCapteur":"CAPTEUR_54","etat":"ALLUME"},{"idCapteur":2676,"numCapteur":55,"intCapteur":0,"idenCapteur":"CAPTEUR_55","etat":"ALLUME"},{"idCapteur":2677,"numCapteur":56,"intCapteur":0,"idenCapteur":"CAPTEUR_56","etat":"ALLUME"},{"idCapteur":2678,"numCapteur":57,"intCapteur":0,"idenCapteur":"CAPTEUR_57","etat":"ALLUME"},{"idCapteur":2679,"numCapteur":58,"intCapteur":0,"idenCapteur":"CAPTEUR_58","etat":"ALLUME"},{"idCapteur":2680,"numCapteur":59,"intCapteur":0,"idenCapteur":"CAPTEUR_59","etat":"ALLUME"},{"idCapteur":2681,"numCapteur":60,"intCapteur":0,"idenCapteur":"CAPTEUR_60","etat":"ALLUME"},{"idCapteur":2682,"numCapteur":61,"intCapteur":0,"idenCapteur":"CAPTEUR_61","etat":"ALLUME"},{"idCapteur":2683,"numCapteur":62,"intCapteur":0,"idenCapteur":"CAPTEUR_62","etat":"ALLUME"},{"idCapteur":2684,"numCapteur":63,"intCapteur":0,"idenCapteur":"CAPTEUR_63","etat":"ALLUME"},{"idCapteur":2685,"numCapteur":64,"intCapteur":0,"idenCapteur":"CAPTEUR_64","etat":"ALLUME"},{"idCapteur":2686,"numCapteur":65,"intCapteur":0,"idenCapteur":"CAPTEUR_65","etat":"ALLUME"}]